lethean_vpn/__init__.py
lethean_vpn/lthnvpnc.py
lethean_vpn/lthnvpnd.py
lethean_vpn/lvmgmt.py
lethean_vpn/lib/__init__.py
lethean_vpn/lib/authids.py
lethean_vpn/lib/config.py
lethean_vpn/lib/log.py
lethean_vpn/lib/sdp.py
lethean_vpn/lib/sdps.py
lethean_vpn/lib/service.py
lethean_vpn/lib/service_ha.py
lethean_vpn/lib/service_hac.py
lethean_vpn/lib/service_has.py
lethean_vpn/lib/service_http.py
lethean_vpn/lib/service_mgmt.py
lethean_vpn/lib/service_ovpn.py
lethean_vpn/lib/service_ovpnc.py
lethean_vpn/lib/service_ovpns.py
lethean_vpn/lib/service_stn.py
lethean_vpn/lib/service_syslog.py
lethean_vpn/lib/services.py
lethean_vpn/lib/sessions.py
lethean_vpn/lib/util.py
lethean_vpn-1.0.0.dist-info/LICENSE
lethean_vpn-1.0.0.dist-info/METADATA
lethean_vpn-1.0.0.dist-info/WHEEL
lethean_vpn-1.0.0.dist-info/top_level.txt
lethean_vpn-1.0.0.dist-info/RECORD
