Metadata-Version: 2.1
Name: lethean-vpn
Version: 1.0.0
Summary: Lethean VPN
Home-page: https://lt.hn/en/docs/vpn
Author: Lethean VPN
Author-email: contact@lethean.io
License: GPLv3
Keywords: vpn
Platform: UNKNOWN
Requires-Python: >=3.6
License-File: LICENSE
Requires-Dist: urllib3 (>=1.25.3)
Requires-Dist: python-dateutil
Requires-Dist: syslogmp
Requires-Dist: ed25519
Requires-Dist: cryptography
Requires-Dist: psutil
Requires-Dist: jsonpickle
Requires-Dist: configargparse
Requires-Dist: requests
Requires-Dist: dnspython
